Metadata-Version: 2.1
Name: volume2mesh
Version: 0.3.2
Summary: Add a short description here!
Home-page: https://github.com/theHamsta/volume2mesh/
Author: Stephan Seitz
Author-email: stephan.seitz@fau.de
License: gpl3
Platform: any
Classifier: Development Status :: 4 - Beta
Classifier: Programming Language :: Python
Provides-Extra: testing
